rtml_ml/__init__.py
rtml_ml/data.py
rtml_ml/experiment_tracking_api.py
rtml_ml/features.py
rtml_ml/hyperparams.py
rtml_ml/model_factory.py
rtml_ml/plot.py
rtml_ml/predict.py
rtml_ml/preprocessing.py
rtml_ml/train.py
rtml_ml-0.1.4.dist-info/METADATA
rtml_ml-0.1.4.dist-info/WHEEL
rtml_ml-0.1.4.dist-info/RECORD
