Metadata-Version: 2.1
Name: rtml-ml
Version: 0.1.4
Summary: 
Author: Paulescu
Author-email: plabartabajo@gmail.com
Requires-Python: >=3.10,<3.11
Classifier: Programming Language :: Python :: 3
Classifier: Programming Language :: Python :: 3.10
Requires-Dist: bokeh (==2.4.3)
Requires-Dist: comet-ml (>=3.37.1,<4.0.0)
Requires-Dist: fire (>=0.5.0,<0.6.0)
Requires-Dist: rtml-tools (>=0.2.0,<0.3.0)
Requires-Dist: scikit-learn (>=1.4.0,<2.0.0)
Requires-Dist: seaborn (>=0.13.2,<0.14.0)
Requires-Dist: sweetviz (>=2.3.1,<3.0.0)
Requires-Dist: ta-lib (>=0.4.28,<0.5.0)
